pyuu/icl/__init__.py
pyuu/icl/inf.py
pyuu/icl/itv.py
pyuu/icl/itvset_rbtree.py
pyuu/icl/itvset_treap.py
pyuu.icl-0.0.1.dist-info/METADATA
pyuu.icl-0.0.1.dist-info/WHEEL
pyuu.icl-0.0.1.dist-info/top_level.txt
pyuu.icl-0.0.1.dist-info/RECORD
